SupervisedClustering/__init__.py
SupervisedClustering/models.py
SupervisedClustering-0.0.5.dist-info/LICENSE
SupervisedClustering-0.0.5.dist-info/METADATA
SupervisedClustering-0.0.5.dist-info/WHEEL
SupervisedClustering-0.0.5.dist-info/top_level.txt
SupervisedClustering-0.0.5.dist-info/RECORD
