Metadata-Version: 2.1
Name: SupervisedClustering
Version: 0.0.5
Summary: SupervisedClustering is a Python package to apply clustering algorithms in supervised learning problems.
Home-page: https://github.com/FabioScielzoOrtiz/SupervisedClustering_Package
Author: Fabio Scielzo Ortiz
Author-email: fabioscielzo98@gmail.com
Classifier: Programming Language :: Python :: 3
Classifier: License :: OSI Approved :: MIT License
Classifier: Operating System :: OS Independent
Requires-Python: >=3.7
License-File: LICENSE
Requires-Dist: pandas
Requires-Dist: numpy
